tfx_moe/__init__.py
tfx_moe/core.py
tfx_moe-0.1.0.dist-info/METADATA
tfx_moe-0.1.0.dist-info/WHEEL
tfx_moe-0.1.0.dist-info/top_level.txt
tfx_moe-0.1.0.dist-info/RECORD
