Metadata-Version: 2.4
Name: tfx-moe
Version: 0.1.0
Summary: Multi-output evaluator TFX component for deep learning models that utilize TensorFlow and TensorFlow Extended.
Home-page: https://github.com/real-ahmed-moussa/tfx-multioutput-evaluator
Author: Dr. Ahmed Moussa
Author-email: ahmedyosrihamdy@gmail.com
License: MIT
Classifier: Programming Language :: Python :: 3
Classifier: License :: OSI Approved :: MIT License
Classifier: Operating System :: OS Independent
Classifier: Topic :: Scientific/Engineering :: Artificial Intelligence
Requires-Python: >=3.10.8
Requires-Dist: tfx<2.0,>=1.15.1
Requires-Dist: tensorflow<2.16,>=2.15.1
Requires-Dist: tensorflow-transform<2.0,>=1.15.0
Dynamic: author
Dynamic: author-email
Dynamic: classifier
Dynamic: description
Dynamic: description-content-type
Dynamic: home-page
Dynamic: license
Dynamic: requires-dist
Dynamic: requires-python
Dynamic: summary
